THCustomLogger/__init__.py
THCustomLogger/config.py
THCustomLogger/logger_setup.py
thcustomlogger-0.3.0.dist-info/METADATA
thcustomlogger-0.3.0.dist-info/WHEEL
thcustomlogger-0.3.0.dist-info/licenses/LICENSE
thcustomlogger-0.3.0.dist-info/RECORD
