Metadata-Version: 2.4
Name: THCustomLogger
Version: 0.3.0
Summary: A custom logging package with multiline formatting
Project-URL: Homepage, https://github.com/TabgoHotel/CustomLogger.git
Project-URL: Bug Tracker, https://github.com/TabgoHotel/CustomLogger/issues
Project-URL: Changelog, https://github.com/TabgoHotel/CustomLogger/blob/main/changelog.md
Author-email: Tyler Haunreiter <silentbox23@gmail.com>
License: MIT
License-File: LICENSE
Classifier: Development Status :: 4 - Beta
Classifier: Intended Audience :: Developers
Classifier: License :: OSI Approved :: MIT License
Classifier: Operating System :: OS Independent
Classifier: Programming Language :: Python :: 3
Classifier: Programming Language :: Python :: 3.8
Classifier: Programming Language :: Python :: 3.9
Classifier: Programming Language :: Python :: 3.10
Classifier: Programming Language :: Python :: 3.11
Classifier: Programming Language :: Python :: 3.12
Classifier: Topic :: System :: Logging
Requires-Python: >=3.8
Requires-Dist: colorlog>=6.9.0
